{
    "id": 2,
    "title": "Form 2",
    "description": "This test form",
    "createdDate": "2024/01/01",
    "fee": "10000",
    "sections": [
        {
            "id": "stepper-1",
            "type": "stepper",
            "showReceipt": false,
            "steps": [
                {
                    "id": "step-1",
                    "label": "Insured Object Information",
                    "title": "General Information",
                    "fields": [
                        {
                            "id": "fullName2",
                            "fieldCode": "fullName",
                            "label": "Full Name2",
                            "fieldType": "input",
                            "prefilled": "",
                            "validationRules": {
                                "required": true,
                                "max": 50,
                                "regex": "^[a-zA-Z"
                            }
                        },
                        {
                            "id": "dateOfBirth2",
                            "label": "Date of Birth",
                            "fieldType": "datePicker",
                            "fieldCode": "dateOfBirth2",
                            "prefilled": "",
                            "validationRules": {
                                "required": true,
                                "max": 70,
                                "minDate": "20/05/2024"
                            }
                        },
                        {
                            "id": "gender2",
                            "label": "Gender",
                            "fieldType": "dropdown",
                            "fieldCode": "gender2",
                            "dropdownValues": [
                                {
                                    "id": "Male",
                                    "label": "Male"
                                },
                                {
                                    "id": "Female",
                                    "label": "Female"
                                }
                            ],
                            "prefilled": "Male",
                            "validationRules": {
                                "required": true
                            }
                        },
                        {
                            "id": "passportNumber2",
                            "label": "ID/Passport Number",
                            "fieldCode": "passportNumber2",
                            "fieldType": "input",
                            "prefilled": "",
                            "validationRules": {
                                "required": true,
                                "max": 50,
                                "regex": "^[a-zA-Z"
                            }
                        },
                        {
                            "id": "dateOfIssued2",
                            "label": "Date of Issued",
                            "fieldType": "datePicker",
                            "fieldCode": "dateOfIssued2",
                            "prefilled": "",
                            "validationRules": {
                                "required": true,
                                "max": 50,
                                "regex": "^[a-zA-Z"
                            }
                        },
                        {
                            "id": "placeOfIssued2",
                            "label": "Place of Issued",
                            "fieldType": "input",
                            "fieldCode": "placeOfIssued2",
                            "prefilled": "",
                            "validationRules": {
                                "required": false,
                                "max": 50,
                                "regex": "^[a-zA-Z"
                            }
                        },
                        {
                            "id": "address",
                            "label": "Address",
                            "fieldCode": "address2",
                            "fieldType": "input",
                            "prefilled": "",
                            "validationRules": {
                                "required": false,
                                "max": 100
                            }
                        }
                    ]
                },
                {
                    "id": "step-2",
                    "label": "Insurance Package",
                    "title": "General Information",
                    "fields": [
                        {
                            "id": "insurancePackage3",
                            "label": "Insurance Package",
                            "fieldType": "dropdown",
                            "fieldCode": "insurancePackage3",
                            "dropdownValues": [
                                {
                                    "id": "golden",
                                    "label": "Golden"
                                },
                                {
                                    "id": "silver",
                                    "label": "Silver"
                                },
                                {
                                    "id": "bronze",
                                    "label": "Bronze"
                                }
                            ],
                            "prefilled": "bronze",
                            "validationRules": {
                                "required": true
                            }
                        },
                        {
                            "id": "dateOfBirth3",
                            "label": "Date of Birth",
                            "fieldType": "datePicker",
                            "fieldCode": "dateOfBirth3",
                            "prefilled": "",
                            "validationRules": {
                                "required": true,
                                "max": 70,
                                "minDate": "20/05/2024"
                            }
                        },
                        {
                            "id": "dateOfIssued3",
                            "label": "Date of Issued",
                            "fieldType": "datePicker",
                            "fieldCode": "dateOfIssued3",
                            "prefilled": "",
                            "validationRules": {
                                "required": true,
                                "max": 50,
                                "regex": "^[a-zA-Z"
                            }
                        },
                        {
                            "id": "insuranceCheckbox3",
                            "fieldType": "checkbox",
                            "fieldCode": "insuranceCheckbox3",
                            "title": "Mandatory Insurance Benefits",
                            "checkboxValues": [
                                {
                                    "id": "checkbox1",
                                    "label": "Death and permenant total disability due to accident/year.",
                                    "checked": true,
                                    "disabled": true,
                                    "helperText": "Insurance amount: $50.000"
                                },
                                {
                                    "id": "checkbox2",
                                    "label": "Death and permenant total disability due to accident/year.",
                                    "checked": true,
                                    "disabled": true,
                                    "helperText": "Insurance amount: $50.000"
                                },
                                {
                                    "id": "checkbox3",
                                    "label": "Death and permenant total disability due to accident/year.",
                                    "checked": true,
                                    "disabled": true,
                                    "helperText": "Insurance amount: $50.000"
                                },
                                {
                                    "id": "checkbox4",
                                    "label": "Death and permenant total disability due to accident/year.",
                                    "checked": true,
                                    "disabled": true,
                                    "helperText": "Insurance amount: $50.000"
                                }
                            ]
                        },
                        {
                            "id": "insuranceCheckbox3",
                            "fieldType": "checkbox",
                            "fieldCode": "insuranceCheckbox1",
                            "title": "Additional Insurance Benefits",
                            "checkboxValues": [
                                {
                                    "id": "checkbox1",
                                    "label": "Death and permenant total disability due to accident/year.",
                                    "checked": false,
                                    "disabled": false,
                                    "helperText": "Insurance amount: $50.000"
                                },
                                {
                                    "id": "checkbox2",
                                    "label": "Death and permenant total disability due to accident/year.",
                                    "checked": false,
                                    "disabled": false,
                                    "helperText": "Insurance amount: $50.000"
                                }
                            ]
                        }
                    ]
                }
            ]
        }
    ]
}